gradle.properties
hexdoc_hexposition/__gradle_version__.py
hexdoc_hexposition/__init__.py
hexdoc_hexposition/__version__.py
hexdoc_hexposition/_hooks.py
hexdoc_hexposition/py.typed
hexdoc_hexposition/_export/.gitignore
hexdoc_hexposition/_export/__init__.py
hexdoc_hexposition/_export/generated/__init__.py
hexdoc_hexposition/_export/generated/hexposition.hexdoc.json
hexdoc_hexposition/_export/generated/hexposition.patterns.hexdoc.json
hexdoc_hexposition/_export/generated/assets/hexcasting/lang/en_us.flatten.json5
hexdoc_hexposition/_export/generated/assets/hexcasting/patchouli_books/thehexbook/en_us/categories/scrying.json
hexdoc_hexposition/_export/generated/assets/hexcasting/patchouli_books/thehexbook/en_us/entries/patterns/enlightened_patterns.json
hexdoc_hexposition/_export/generated/assets/hexcasting/patchouli_books/thehexbook/en_us/entries/patterns/perlin.json
hexdoc_hexposition/_export/generated/assets/hexcasting/patchouli_books/thehexbook/en_us/entries/patterns/special_raycasts.json
hexdoc_hexposition/_export/generated/assets/hexcasting/patchouli_books/thehexbook/en_us/entries/patterns/scrying/blocks.json
hexdoc_hexposition/_export/generated/assets/hexcasting/patchouli_books/thehexbook/en_us/entries/patterns/scrying/entities.json
hexdoc_hexposition/_export/generated/assets/hexcasting/patchouli_books/thehexbook/en_us/entries/patterns/scrying/environment.json
hexdoc_hexposition/_export/generated/assets/hexcasting/patchouli_books/thehexbook/en_us/entries/patterns/scrying/food.json
hexdoc_hexposition/_export/generated/assets/hexcasting/patchouli_books/thehexbook/en_us/entries/patterns/scrying/identifiers.json
hexdoc_hexposition/_export/generated/assets/hexcasting/patchouli_books/thehexbook/en_us/entries/patterns/scrying/item.json
hexdoc_hexposition/_export/generated/assets/hexcasting/patchouli_books/thehexbook/en_us/entries/patterns/scrying/media.json
hexdoc_hexposition-1.3.0.1.0.0.dist-info/METADATA
hexdoc_hexposition-1.3.0.1.0.0.dist-info/WHEEL
hexdoc_hexposition-1.3.0.1.0.0.dist-info/entry_points.txt
hexdoc_hexposition-1.3.0.1.0.0.dist-info/licenses/LICENSE
hexdoc_hexposition-1.3.0.1.0.0.dist-info/RECORD
